{"ELEMENTCOUNT":"15","ENTITY":"customer","TYPE":"DB","DATA":"{\"2\":{\"subelements\":{\"1\":{\"id\":1,\"populate\":\"\"}},\"rules\":[{\"type\":\"rule_function\",\"parameters\":[\"wsNoRegistration\",\"EQ\",\"1\",\"disable\"]},{\"type\":\"rule_function\",\"parameters\":[\"wsSetting,login_with_email\",\"EQ\",\"1\",\"disable\"]}],\"mandatory\":1,\"system\":1,\"unique\":1,\"links\":[],\"id\":2,\"label\":\"Login name \",\"x\":5,\"y\":5,\"type\":\"text_large\",\"column\":\"LOGINNAME\",\"children\":2,\"attributes\":{\"zfsize\":\"\",\"zfmaxlength\":\"\",\"zfrows\":\"\",\"zfrepeatable\":0,\"zfguidelines\":\"\"}},\"3\":{\"subelements\":{\"1\":{\"id\":1,\"populate\":\"\",\"label\":\"Password\",\"hide\":1},\"2\":{\"id\":2,\"populate\":\"\",\"label\":\"Repeat\",\"hide\":1}},\"rules\":[{\"type\":\"rule_function\",\"parameters\":[\"wsNoRegistration\",\"EQ\",\"1\",\"disable\"]},{\"type\":\"rule_function\",\"parameters\":[\"wsSetting,generate_password\",\"EQ\",\"1\",\"disable\"]}],\"mandatory\":1,\"system\":1,\"links\":[],\"id\":3,\"label\":\"Password \",\"x\":5,\"y\":57,\"type\":\"password2\",\"column\":\"PASSWORD\",\"children\":3,\"attributes\":{\"zfsize\":\"\",\"zfmaxlength\":\"\",\"zfrows\":\"\",\"zfrepeatable\":0,\"zfguidelines\":\"\"}},\"12\":{\"subelements\":{\"1\":{\"id\":1,\"populate\":\"\"}},\"rules\":[{\"type\":\"rule_function\",\"parameters\":[\"wsNoRegistration\",\"EQ\",\"0\",\"unique\"]}],\"mandatory\":1,\"system\":1,\"links\":[],\"id\":12,\"label\":\"E-mail \",\"x\":5,\"y\":120,\"type\":\"email\",\"column\":\"EMAIL\",\"children\":2,\"attributes\":{\"zfsize\":\"\",\"zfmaxlength\":\"\",\"zfrows\":\"\",\"zfrepeatable\":0,\"zfguidelines\":\"\"}},\"18\":{\"subelements\":{\"1\":{\"id\":1,\"populate\":\"\"}},\"rules\":[],\"links\":[],\"id\":18,\"label\":\"Prefix \",\"x\":5,\"y\":172,\"type\":\"text_small\",\"column\":\"MIDDLENAME\",\"children\":2,\"attributes\":[]},\"17\":{\"subelements\":{\"1\":{\"id\":1,\"populate\":\"\"}},\"rules\":[],\"mandatory\":1,\"links\":[],\"id\":17,\"label\":\"Initials \",\"x\":5,\"y\":224,\"type\":\"text_small\",\"column\":\"INITIALS\",\"children\":2,\"attributes\":[]},\"5\":{\"subelements\":{\"1\":{\"id\":1,\"populate\":\"\",\"hide\":1}},\"rules\":[],\"mandatory\":1,\"links\":[],\"id\":5,\"label\":\"Surname \",\"x\":5,\"y\":276,\"type\":\"text_large\",\"column\":\"LASTNAME\",\"children\":2,\"attributes\":[]},\"8\":{\"subelements\":{\"1\":{\"id\":1,\"populate\":\"\",\"hide\":1}},\"rules\":[],\"links\":[],\"id\":8,\"label\":\"Company \",\"x\":5,\"y\":328,\"type\":\"text_large\",\"column\":\"COMPANY\",\"children\":2,\"attributes\":[]},\"9\":{\"subelements\":{\"1\":{\"id\":1,\"populate\":\"\",\"hide\":1}},\"rules\":[],\"mandatory\":1,\"links\":[],\"id\":9,\"label\":\"Address \",\"x\":5,\"y\":380,\"type\":\"text_large\",\"column\":\"ADDRESS\",\"children\":2,\"attributes\":[]},\"6\":{\"subelements\":{\"1\":{\"id\":1,\"populate\":\"\",\"hide\":1}},\"rules\":[],\"mandatory\":1,\"links\":[],\"id\":6,\"label\":\"Zip \",\"x\":5,\"y\":432,\"type\":\"text_small\",\"column\":\"ZIP\",\"children\":2,\"attributes\":[]},\"10\":{\"subelements\":{\"1\":{\"id\":1,\"populate\":\"\"}},\"rules\":[],\"mandatory\":1,\"links\":[],\"id\":10,\"label\":\"City \",\"x\":5,\"y\":484,\"type\":\"text_large\",\"column\":\"CITY\",\"children\":2,\"attributes\":[]},\"11\":{\"subelements\":{\"1\":{\"id\":1,\"populate\":\"\",\"hide\":1}},\"rules\":[],\"links\":[],\"id\":11,\"label\":\"State \",\"x\":5,\"y\":536,\"type\":\"text_large\",\"column\":\"STATE\",\"children\":2,\"attributes\":[]},\"20\":{\"subelements\":{\"1\":{\"id\":1,\"populate\":\"\"}},\"rules\":[],\"system\":1,\"links\":[],\"id\":20,\"label\":\"Country \",\"x\":5,\"y\":588,\"type\":\"country\",\"column\":\"COUNTRY\",\"children\":2,\"attributes\":[]},\"13\":{\"subelements\":{\"1\":{\"id\":1,\"populate\":\"\"}},\"rules\":[{\"type\":\"rule_function\",\"parameters\":[\"wsNoRegistration\",\"EQ\",\"1\",\"disable\"]}],\"links\":[],\"id\":13,\"label\":\"Telephone \",\"x\":5,\"y\":639,\"type\":\"simple_phone\",\"column\":\"PHONE\",\"children\":2,\"attributes\":[]},\"21\":{\"subelements\":{\"1\":{\"id\":1,\"populate\":1}},\"rules\":[{\"type\":\"rule_function\",\"parameters\":[\"wsNoRegistration\",\"EQ\",\"1\",\"disable\"]}],\"links\":[],\"id\":21,\"label\":\"Newsletter? \",\"x\":5,\"y\":691,\"type\":\"checkbox\",\"column\":\"NEWSLETTER\",\"children\":2,\"attributes\":[]},\"15\":{\"subelements\":{\"1\":{\"id\":1,\"populate\":\"\"}},\"rules\":[],\"mandatory\":1,\"links\":[],\"id\":15,\"label\":\"Type this code \",\"x\":5,\"y\":735,\"type\":\"captcha\",\"column\":\"captcha\",\"children\":2,\"attributes\":[]}}","LABEL":"New customer","PROJECT":"fws","ID":"58","NAME":"register"}